{"0":{"item":0,"appearances":2,"arrays_present":["one","two"],"indexes":{"index_of_one":[31],"index_of_two":[15],"arrays":["one","two"]}},"1":{"item":1,"appearances":2,"arrays_present":["one"],"indexes":{"index_of_one":[1,14],"index_of_two":[],"arrays":["one"]}},"3":{"item":3,"appearances":1,"arrays_present":["two"],"indexes":{"index_of_one":[],"index_of_two":[28],"arrays":["two"]}},"4":{"item":4,"appearances":2,"arrays_present":["two","two"],"indexes":{"index_of_one":[],"index_of_two":[0,49],"arrays":["two","two"]}},"6":{"item":6,"appearances":1,"arrays_present":["one"],"indexes":{"index_of_one":[41],"index_of_two":[],"arrays":["one"]}},"8":{"item":8,"appearances":1,"arrays_present":["two"],"indexes":{"index_of_one":[],"index_of_two":[31],"arrays":["two"]}},"9":{"item":9,"appearances":2,"arrays_present":["one","two"],"indexes":{"index_of_one":[21],"index_of_two":[7],"arrays":["one","two"]}},"10":{"item":10,"appearances":1,"arrays_present":["two"],"indexes":{"index_of_one":[],"index_of_two":[11],"arrays":["two"]}},"11":{"item":11,"appearances":1,"arrays_present":["one"],"indexes":{"index_of_one":[39],"index_of_two":[],"arrays":["one"]}},"12":{"item":12,"appearances":2,"arrays_present":["one"],"indexes":{"index_of_one":[33,40],"index_of_two":[],"arrays":["one"]}},"13":{"item":13,"appearances":2,"arrays_present":["one","two"],"indexes":{"index_of_one":[8],"index_of_two":[40],"arrays":["one","two"]}},"14":{"item":14,"appearances":1,"arrays_present":["two"],"indexes":{"index_of_one":[],"index_of_two":[30],"arrays":["two"]}},"15":{"item":15,"appearances":1,"arrays_present":["one"],"indexes":{"index_of_one":[15],"index_of_two":[],"arrays":["one"]}},"16":{"item":16,"appearances":1,"arrays_present":["two"],"indexes":{"index_of_one":[],"index_of_two":[33],"arrays":["two"]}},"21":{"item":21,"appearances":1,"arrays_present":["one"],"indexes":{"index_of_one":[35],"index_of_two":[],"arrays":["one"]}},"22":{"item":22,"appearances":1,"arrays_present":["one"],"indexes":{"index_of_one":[37],"index_of_two":[],"arrays":["one"]}},"24":{"item":24,"appearances":1,"arrays_present":["two"],"indexes":{"index_of_one":[],"index_of_two":[17],"arrays":["two"]}},"25":{"item":25,"appearances":1,"arrays_present":["two"],"indexes":{"index_of_one":[],"index_of_two":[45],"arrays":["two"]}},"26":{"item":26,"appearances":2,"arrays_present":["one","two"],"indexes":{"index_of_one":[29],"index_of_two":[26],"arrays":["one","two"]}},"27":{"item":27,"appearances":1,"arrays_present":["two"],"indexes":{"index_of_one":[],"index_of_two":[35],"arrays":["two"]}},"28":{"item":28,"appearances":2,"arrays_present":["one","two"],"indexes":{"index_of_one":[2],"index_of_two":[18],"arrays":["one","two"]}},"31":{"item":31,"appearances":2,"arrays_present":["two","two"],"indexes":{"index_of_one":[],"index_of_two":[3,9],"arrays":["two","two"]}},"32":{"item":32,"appearances":1,"arrays_present":["one"],"indexes":{"index_of_one":[7],"index_of_two":[],"arrays":["one"]}},"33":{"item":33,"appearances":3,"arrays_present":["one","two"],"indexes":{"index_of_one":[4,19],"index_of_two":[25],"arrays":["one","two"]}},"34":{"item":34,"appearances":1,"arrays_present":["one"],"indexes":{"index_of_one":[20],"index_of_two":[],"arrays":["one"]}},"35":{"item":35,"appearances":1,"arrays_present":["one"],"indexes":{"index_of_one":[13],"index_of_two":[],"arrays":["one"]}},"38":{"item":38,"appearances":3,"arrays_present":["two","two"],"indexes":{"index_of_one":[],"index_of_two":[10,36,39],"arrays":["two","two"]}},"40":{"item":40,"appearances":2,"arrays_present":["one","two"],"indexes":{"index_of_one":[18],"index_of_two":[21],"arrays":["one","two"]}},"45":{"item":45,"appearances":1,"arrays_present":["two"],"indexes":{"index_of_one":[],"index_of_two":[38],"arrays":["two"]}},"46":{"item":46,"appearances":2,"arrays_present":["one","two"],"indexes":{"index_of_one":[30],"index_of_two":[5],"arrays":["one","two"]}},"47":{"item":47,"appearances":2,"arrays_present":["one"],"indexes":{"index_of_one":[25,44],"index_of_two":[],"arrays":["one"]}},"49":{"item":49,"appearances":2,"arrays_present":["one","two"],"indexes":{"index_of_one":[22],"index_of_two":[22],"arrays":["one","two"]}},"50":{"item":50,"appearances":2,"arrays_present":["one","two"],"indexes":{"index_of_one":[9],"index_of_two":[8],"arrays":["one","two"]}},"51":{"item":51,"appearances":1,"arrays_present":["one"],"indexes":{"index_of_one":[3],"index_of_two":[],"arrays":["one"]}},"52":{"item":52,"appearances":2,"arrays_present":["one"],"indexes":{"index_of_one":[28,34],"index_of_two":[],"arrays":["one"]}},"53":{"item":53,"appearances":2,"arrays_present":["one","two"],"indexes":{"index_of_one":[0],"index_of_two":[44],"arrays":["one","two"]}},"54":{"item":54,"appearances":1,"arrays_present":["one"],"indexes":{"index_of_one":[6],"index_of_two":[],"arrays":["one"]}},"55":{"item":55,"appearances":3,"arrays_present":["one","two"],"indexes":{"index_of_one":[16,38],"index_of_two":[20],"arrays":["one","two"]}},"56":{"item":56,"appearances":1,"arrays_present":["one"],"indexes":{"index_of_one":[17],"index_of_two":[],"arrays":["one"]}},"57":{"item":57,"appearances":1,"arrays_present":["two"],"indexes":{"index_of_one":[],"index_of_two":[47],"arrays":["two"]}},"58":{"item":58,"appearances":2,"arrays_present":["one","two"],"indexes":{"index_of_one":[24],"index_of_two":[24],"arrays":["one","two"]}},"59":{"item":59,"appearances":2,"arrays_present":["one","two"],"indexes":{"index_of_one":[49],"index_of_two":[2],"arrays":["one","two"]}},"62":{"item":62,"appearances":2,"arrays_present":["two","two"],"indexes":{"index_of_one":[],"index_of_two":[12,42],"arrays":["two","two"]}},"65":{"item":65,"appearances":1,"arrays_present":["one"],"indexes":{"index_of_one":[32],"index_of_two":[],"arrays":["one"]}},"66":{"item":66,"appearances":2,"arrays_present":["one","two"],"indexes":{"index_of_one":[12],"index_of_two":[14],"arrays":["one","two"]}},"67":{"item":67,"appearances":1,"arrays_present":["one"],"indexes":{"index_of_one":[36],"index_of_two":[],"arrays":["one"]}},"69":{"item":69,"appearances":2,"arrays_present":["one","two"],"indexes":{"index_of_one":[23],"index_of_two":[6],"arrays":["one","two"]}},"70":{"item":70,"appearances":2,"arrays_present":["one","two"],"indexes":{"index_of_one":[5],"index_of_two":[32],"arrays":["one","two"]}},"72":{"item":72,"appearances":2,"arrays_present":["one","two"],"indexes":{"index_of_one":[26],"index_of_two":[46],"arrays":["one","two"]}},"73":{"item":73,"appearances":1,"arrays_present":["one"],"indexes":{"index_of_one":[42],"index_of_two":[],"arrays":["one"]}},"74":{"item":74,"appearances":1,"arrays_present":["one"],"indexes":{"index_of_one":[11],"index_of_two":[],"arrays":["one"]}},"75":{"item":75,"appearances":2,"arrays_present":["one","two"],"indexes":{"index_of_one":[46],"index_of_two":[43],"arrays":["one","two"]}},"76":{"item":76,"appearances":1,"arrays_present":["two"],"indexes":{"index_of_one":[],"index_of_two":[19],"arrays":["two"]}},"83":{"item":83,"appearances":2,"arrays_present":["two","two"],"indexes":{"index_of_one":[],"index_of_two":[29,34],"arrays":["two","two"]}},"84":{"item":84,"appearances":1,"arrays_present":["two"],"indexes":{"index_of_one":[],"index_of_two":[13],"arrays":["two"]}},"85":{"item":85,"appearances":1,"arrays_present":["one"],"indexes":{"index_of_one":[45],"index_of_two":[],"arrays":["one"]}},"86":{"item":86,"appearances":1,"arrays_present":["two"],"indexes":{"index_of_one":[],"index_of_two":[1],"arrays":["two"]}},"88":{"item":88,"appearances":1,"arrays_present":["one"],"indexes":{"index_of_one":[48],"index_of_two":[],"arrays":["one"]}},"91":{"item":91,"appearances":2,"arrays_present":["two","two"],"indexes":{"index_of_one":[],"index_of_two":[4,41],"arrays":["two","two"]}},"92":{"item":92,"appearances":3,"arrays_present":["one","two"],"indexes":{"index_of_one":[27],"index_of_two":[37,48],"arrays":["one","two"]}},"95":{"item":95,"appearances":1,"arrays_present":["one"],"indexes":{"index_of_one":[47],"index_of_two":[],"arrays":["one"]}},"96":{"item":96,"appearances":2,"arrays_present":["two","two"],"indexes":{"index_of_one":[],"index_of_two":[16,27],"arrays":["two","two"]}},"97":{"item":97,"appearances":1,"arrays_present":["two"],"indexes":{"index_of_one":[],"index_of_two":[23],"arrays":["two"]}},"98":{"item":98,"appearances":2,"arrays_present":["one"],"indexes":{"index_of_one":[10,43],"index_of_two":[],"arrays":["one"]}}}